beautifulprint/__init__.py
beautifulprint/bprint.py
beautifulprint/colors.py
beautifulprint/kvstorage.py
beautifulprint/old.py
beautifulprint/packing.py
beautifulprint/theme.py
beautifulprint/themes.py
beautifulprint/util.py
printbeautifully-0.2.0.dist-info/METADATA
printbeautifully-0.2.0.dist-info/WHEEL
printbeautifully-0.2.0.dist-info/top_level.txt
printbeautifully-0.2.0.dist-info/RECORD
