Metadata-Version: 2.1
Name: printbeautifully
Version: 0.2.0
Summary: Pretty print but it's prettier than pretty print
Home-page: https://github.com/FAReTek1/beautifulprint
Author: faretek1
Author-email: 
License: MIT
